LICENSE.txt
MANIFEST.in
README.rst
gpl.txt
setup.cfg
setup.py
py_bonemat_abaqus/__init__.py
py_bonemat_abaqus/calc.py
py_bonemat_abaqus/classes.py
py_bonemat_abaqus/command_line.py
py_bonemat_abaqus/data_import.py
py_bonemat_abaqus/data_output.py
py_bonemat_abaqus/general.py
py_bonemat_abaqus/run.py
py_bonemat_abaqus/version.py
py_bonemat_abaqus.egg-info/PKG-INFO
py_bonemat_abaqus.egg-info/SOURCES.txt
py_bonemat_abaqus.egg-info/dependency_links.txt
py_bonemat_abaqus.egg-info/entry_points.txt
py_bonemat_abaqus.egg-info/not-zip-safe
py_bonemat_abaqus.egg-info/requires.txt
py_bonemat_abaqus.egg-info/top_level.txt
py_bonemat_abaqus/example/example_abaqus_mesh.inp
py_bonemat_abaqus/example/example_ct_data.vtk
py_bonemat_abaqus/example/example_parameters.txt
py_bonemat_abaqus/tests/__init__.py
py_bonemat_abaqus/tests/tests.py
py_bonemat_abaqus/tests/tests_functional.py