Metadata-Version: 1.1
Name: py-bonemat-abaqus
Version: 1.0.6
Summary: Assign material properties of bone to a finite element mesh
Home-page: http://github.com/elisepegg/py_bonemat_abaqus
Author: Elise Pegg
Author-email: e.c.pegg@bath.ac.uk
License: GPLv3
Keywords: bone,material,finite element,medical,science,engineering
Platform: UNKNOWN
Classifier: Development Status :: 3 - Alpha
Classifier: License :: OSI Approved :: GNU General Public License v3 or later (GPLv3+)
Classifier: Programming Language :: Python :: 2
Classifier: Programming Language :: Python :: 2.6
Classifier: Programming Language :: Python :: 2.7
Classifier: Intended Audience :: Science/Research
Classifier: Topic :: Scientific/Engineering :: Medical Science Apps.
Classifier: Natural Language :: English
